Metadata-Version: 2.4
Name: pyitlib
Version: 0.3.1
Summary: A library of information-theoretic methods
Home-page: https://github.com/pafoster/pyitlib
Download-URL: https://github.com/pafoster/pyitlib/archive/0.3.1.tar.gz
Author: Peter Foster
Author-email: pyitlib@gmx.us
License: MIT
Keywords: entropy,information theory,Shannon information,uncertainty,correlation,statistics,machine learning,data analysis,data science
Classifier: Development Status :: 4 - Beta
Classifier: Intended Audience :: Science/Research
Classifier: License :: OSI Approved :: MIT License
Classifier: Natural Language :: English
Classifier: Programming Language :: Python :: 3
Classifier: Topic :: Scientific/Engineering :: Artificial Intelligence
Classifier: Topic :: Scientific/Engineering :: Information Analysis
License-File: LICENSE
Requires-Dist: pandas>=0.20.2
Requires-Dist: numpy>=1.9.2
Requires-Dist: scikit-learn>=0.16.0
Requires-Dist: scipy>=1.0.1
Dynamic: author
Dynamic: author-email
Dynamic: classifier
Dynamic: description
Dynamic: download-url
Dynamic: home-page
Dynamic: keywords
Dynamic: license
Dynamic: license-file
Dynamic: requires-dist
Dynamic: summary
